MANIFEST.in
README.md
requirements.txt
setup.cfg
setup.py
hucache/__init__.py
hucache/cache.py
hucache/constants.py
hucache/serializer.py
hucache/store.py
hucache.egg-info/PKG-INFO
hucache.egg-info/SOURCES.txt
hucache.egg-info/dependency_links.txt
hucache.egg-info/requires.txt
hucache.egg-info/top_level.txt